numbasom/__init__.py
numbasom/core.py
numbasom/viz.py
numbasom-0.1.0.dist-info/METADATA
numbasom-0.1.0.dist-info/WHEEL
numbasom-0.1.0.dist-info/licenses/LICENSE
numbasom-0.1.0.dist-info/RECORD
