Metadata-Version: 2.4
Name: numbasom
Version: 0.1.0
Summary: A Fast Self-Organizing Map Python Library Implemented in Numba
Project-URL: Homepage, https://github.com/nmarincic/numbasom
Project-URL: Documentation, https://nmarincic.github.io/numbasom/
Project-URL: Repository, https://github.com/nmarincic/numbasom
Project-URL: Issues, https://github.com/nmarincic/numbasom/issues
Author-email: Nikola Marincic <nikola.marincic@gmail.com>
License-Expression: Apache-2.0
License-File: LICENSE
Keywords: AI,ML,SOM,kohonen,numba,python,self-organizing map
Classifier: Development Status :: 3 - Alpha
Classifier: Intended Audience :: Developers
Classifier: Intended Audience :: Science/Research
Classifier: License :: OSI Approved :: Apache Software License
Classifier: Programming Language :: Python :: 3
Classifier: Programming Language :: Python :: 3.9
Classifier: Programming Language :: Python :: 3.10
Classifier: Programming Language :: Python :: 3.11
Classifier: Programming Language :: Python :: 3.12
Classifier: Programming Language :: Python :: 3.13
Classifier: Topic :: Scientific/Engineering :: Artificial Intelligence
Requires-Python: >=3.9
Requires-Dist: matplotlib>=3.5
Requires-Dist: numba>=0.57
Requires-Dist: numpy>=1.22
